{
  "erkek": {
    "9": {
      "iyi": "10.20",
      "orta_ustu": "10.21",
      "orta": "10.91",
      "orta_alti": "11.41",
      "dusuk": "12.31"
    },
    "10": {
      "iyi": "10.20",
      "orta_ustu": "10.21",
      "orta": "10.91",
      "orta_alti": "11.41",
      "dusuk": "12.31"
    },
    "11": {
      "iyi": "10.20",
      "orta_ustu": "10.21",
      "orta": "10.91",
      "orta_alti": "11.41",
      "dusuk": "12.31"
    },
    "12": {
      "iyi": "10.20",
      "orta_ustu": "10.21",
      "orta": "10.91",
      "orta_alti": "11.41",
      "dusuk": "12.31"
    },
    "13": {
      "iyi": "10.20",
      "orta_ustu": "10.21",
      "orta": "10.91",
      "orta_alti": "11.41",
      "dusuk": "12.31"
    },
    "14": {
      "iyi": "10.20",
      "orta_ustu": "10.21",
      "orta": "10.91",
      "orta_alti": "11.41",
      "dusuk": "12.31"
    },
    "15": {
      "iyi": "10.20",
      "orta_ustu": "10.21",
      "orta": "10.91",
      "orta_alti": "11.41",
      "dusuk": "12.31"
    }
  },
  "kadın": {
    "9": {
      "iyi": "13.00",
      "orta_ustu": "13.01",
      "orta": "14.51",
      "orta_alti": "15.51",
      "dusuk": "16.61"
    },
    "10": {
      "iyi": "13.00",
      "orta_ustu": "13.01",
      "orta": "14.51",
      "orta_alti": "15.51",
      "dusuk": "16.61"
    },
    "11": {
      "iyi": "13.00",
      "orta_ustu": "13.01",
      "orta": "14.51",
      "orta_alti": "15.51",
      "dusuk": "16.61"
    },
    "12": {
      "iyi": "13.00",
      "orta_ustu": "13.01",
      "orta": "14.51",
      "orta_alti": "15.51",
      "dusuk": "16.61"
    },
    "13": {
      "iyi": "13.00",
      "orta_ustu": "13.01",
      "orta": "14.51",
      "orta_alti": "15.51",
      "dusuk": "16.61"
    },
    "14": {
      "iyi": "13.00",
      "orta_ustu": "13.01",
      "orta": "14.51",
      "orta_alti": "15.51",
      "dusuk": "16.61"
    },
    "15": {
      "iyi": "13.00",
      "orta_ustu": "13.01",
      "orta": "14.51",
      "orta_alti": "15.51",
      "dusuk": "16.61"
    }
  }
}